acceptance/__init__.py
acceptance/conftest.py
acceptance/maybe_unique.py
acceptance/test_auto_correlation_score.py
acceptance/test_crossed_derived_via_rejection.py
acceptance/test_exhaust_combinatoric.py
acceptance/test_general_window.py
acceptance/test_guided_sampling.py
acceptance/test_implied.py
acceptance/test_k_constraint.py
acceptance/test_minimum_trials.py
acceptance/test_mismatch.py
acceptance/test_multiple_cross.py
acceptance/test_pin.py
acceptance/test_reduced_crossing_with_exclude.py
acceptance/test_sample_check.py
acceptance/test_server.py
acceptance/test_stroop.py
acceptance/test_stroop_crossing_with_derived.py
acceptance/test_task_switching_simple.py
acceptance/test_transition_with_three_levels.py
acceptance/test_uniform_combinatoric.py
acceptance/test_weights.py
acceptance/test_window_start.py
sweetpea/__init__.py
sweetpea/_internal/__init__.py
sweetpea/_internal/argcheck.py
sweetpea/_internal/auto_correlation_score.py
sweetpea/_internal/backend.py
sweetpea/_internal/base_constraint.py
sweetpea/_internal/beforestart.py
sweetpea/_internal/block.py
sweetpea/_internal/check_mismatch.py
sweetpea/_internal/combinatorics.py
sweetpea/_internal/constraint.py
sweetpea/_internal/cross_block.py
sweetpea/_internal/derivation_processor.py
sweetpea/_internal/design_graph.py
sweetpea/_internal/design_partition.py
sweetpea/_internal/distribution.py
sweetpea/_internal/encoding_diagram.py
sweetpea/_internal/iter.py
sweetpea/_internal/level.py
sweetpea/_internal/logic.py
sweetpea/_internal/main.py
sweetpea/_internal/metrics.py
sweetpea/_internal/primitive.py
sweetpea/_internal/sample_conversion.py
sweetpea/_internal/server.py
sweetpea/_internal/weight.py
sweetpea/_internal/core/__init__.py
sweetpea/_internal/core/binary.py
sweetpea/_internal/core/cnf.py
sweetpea/_internal/core/simple_sequence.py
sweetpea/_internal/core/tests.py
sweetpea/_internal/core/generate/__init__.py
sweetpea/_internal/core/generate/is_satisfiable.py
sweetpea/_internal/core/generate/sample_ilp.py
sweetpea-0.2.12.dist-info/LICENSE
sweetpea-0.2.12.dist-info/METADATA
sweetpea-0.2.12.dist-info/WHEEL
sweetpea-0.2.12.dist-info/top_level.txt
sweetpea-0.2.12.dist-info/RECORD
