Metadata-Version: 2.1
Name: sweetpea
Version: 0.2.12
Summary: A language for synthesizing randomized experimental designs
Home-page: https://github.com/sweetpea-org/sweetpea-py
Author: Annie Cherkaev, Ben Draut, Ahsan Sajjad Butt, Pierce Darragh, Matthew Flatt, Sirus Shahini, Di Wang
Author-email: annie.cherk@gmail.com, drautb@cs.utah.edu, ahsansbutt@hotmail.com, pierce.darragh@gmail.com, mflatt@cs.utah.edu, sirus.shahini@gmail.com, dwang0127@gmail.com
License: UNKNOWN
Platform: UNKNOWN
Classifier: Programming Language :: Python :: 3
Classifier: License :: OSI Approved :: MIT License
Classifier: Operating System :: OS Independent
License-File: LICENSE
Requires-Dist: ascii-graph
Requires-Dist: appdirs
Requires-Dist: mypy
Requires-Dist: networkx
Requires-Dist: numpy
Requires-Dist: pytest
Requires-Dist: requests
Requires-Dist: tqdm
